quecto/__init__.py
quecto/quecto.py
quecto-1.0.3.dist-info/LICENSE
quecto-1.0.3.dist-info/METADATA
quecto-1.0.3.dist-info/WHEEL
quecto-1.0.3.dist-info/top_level.txt
quecto-1.0.3.dist-info/RECORD
