Metadata-Version: 2.1
Name: quecto
Version: 1.0.3
Summary: The official python wrapper for Quecto, a link shortener
Author: oriionn
License: GNU GENERAL PUBLIC LICENSE
Project-URL: homepage, https://github.com/oriionn/quecto-py
Project-URL: documentation, https://github.com/oriionn/quecto-py#readme
Project-URL: repository, https://github.com/oriionn/quecto-py
Keywords: API,wrapper,quecto,link,shortener,shorten,short
Classifier: Operating System :: OS Independent
Classifier: Programming Language :: Python :: 3
Requires-Python: >=3.7
License-File: LICENSE
Requires-Dist: requests
Requires-Dist: requests-toolbelt
